{
	"h1emubaseweather": {
		"templateName": "h1emubaseweather",
		"overcast": 0,
		"fogDensity": 0,
		"fogFloor": 1,
		"fogGradient": 1,
		"globalPrecipitation": 0,
		"temperature": 0,
		"skyClarity": 0.7,
		"cloudWeight0": 0.16,
		"cloudWeight1": 0.68,
		"cloudWeight2": 0.08,
		"cloudWeight3": 0,
		"transitionTime": 0,
		"sunAxisX": 0,
		"sunAxisY": 0,
		"sunAxisZ": 0,
		"windDirectionX": 100,
		"windDirectionY": 200,
		"windDirectionZ": 300,
		"wind": 5,
		"rainminStrength": 0,
		"rainRampupTimeSeconds": 0,
		"cloudFile": "sky_Z_clouds.dds",
		"stratusCloudTiling": 0,
		"stratusCloudScrollU": 0,
		"stratusCloudScrollV": 0,
		"stratusCloudHeight": 0,
		"cumulusCloudTiling": 0,
		"cumulusCloudScrollU": 0,
		"cumulusCloudScrollV": 0,
		"cumulusCloudHeight": 0,
		"cloudAnimationSpeed": 0.1,
		"cloudSilverLiningThickness": 0.8,
		"cloudSilverLiningBrightness": 0.2,
		"cloudShadows": 1
	},
	"z1br": {
		"templateName": "z1br",
		"overcast": 1,
		"fogDensity": 0.0001733333,
		"fogFloor": 10,
		"fogGradient": 0.0144,
		"globalPrecipitation": 1,
		"temperature": 75,
		"skyClarity": 0,
		"cloudWeight0": 0.05,
		"cloudWeight1": 0,
		"cloudWeight2": 0.05,
		"cloudWeight3": 0.15,
		"transitionTime": 0,
		"sunAxisX": 38,
		"sunAxisY": -15,
		"sunAxisZ": 0,
		"windDirX": -1,
		"windDirY": -0.05,
		"windDirZ": -1,
		"wind": 3,
		"rainminStrength": 0,
		"rainRampupTimeSeconds": 1,
		"cloudFile": "sky_Z_clouds.dds",
		"stratusCloudTiling": 0.3,
		"stratusCloudScrollU": -0.002,
		"stratusCloudScrollV": 0,
		"stratusCloudHeight": 1000,
		"cumulusCloudTiling": 0.2,
		"cumulusCloudScrollU": 0,
		"cumulusCloudScrollV": 0.002,
		"cumulusCloudHeight": 8000,
		"cloudAnimationSpeed": 0,
		"cloudSilverLiningThickness": 0.25,
		"cloudSilverLiningBrightness": 7,
		"cloudShadows": 0.5
	},
	"sunset": {
		"templateName": "sunset",
		"overcast": 0,
		"fogDensity": 0,
		"fogFloor": 1,
		"fogGradient": 1,
		"globalPrecipitation": 123,
		"temperature": 50,
		"skyClarity": 0.10946120217169808,
		"cloudWeight0": 0.5753179865655127,
		"cloudWeight1": 0.4527050241187167,
		"cloudWeight2": 0.6209641091327527,
		"cloudWeight3": 0,
		"transitionTime": 0,
		"sunAxisX": 274,
		"sunAxisY": 23,
		"sunAxisZ": 0,
		"windDirectionX": 193,
		"windDirectionY": 44,
		"windDirectionZ": 98,
		"wind": 9,
		"rainminStrength": 0,
		"rainRampupTimeSeconds": 0,
		"cloudFile": "sky_Z_clouds.dds",
		"stratusCloudTiling": 0,
		"stratusCloudScrollU": 0,
		"stratusCloudScrollV": 0,
		"stratusCloudHeight": 0,
		"cumulusCloudTiling": 0,
		"cumulusCloudScrollU": 0,
		"cumulusCloudScrollV": 0,
		"cumulusCloudHeight": 0,
		"cloudAnimationSpeed": 0.3603743861432199,
		"cloudSilverLiningThickness": 0.1650277968581435,
		"cloudSilverLiningBrightness": 1.5307335036980811,
		"cloudShadows": 0
	},
	"morning": {
		"templateName": "morning",
		"overcast": 0,
		"fogDensity": 0,
		"fogFloor": 1,
		"fogGradient": 1,
		"globalPrecipitation": 106,
		"temperature": 23,
		"skyClarity": 0.5620435783564746,
		"cloudWeight0": 0.5503498662928124,
		"cloudWeight1": 0.7976323138865109,
		"cloudWeight2": 0.28828251786553416,
		"cloudWeight3": 0,
		"transitionTime": 0,
		"sunAxisX": 255,
		"sunAxisY": 238,
		"sunAxisZ": 0,
		"windDirectionX": 275,
		"windDirectionY": 285,
		"windDirectionZ": 354,
		"wind": 86,
		"rainminStrength": 0,
		"rainRampupTimeSeconds": 0,
		"cloudFile": "sky_Z_clouds.dds",
		"stratusCloudTiling": 0,
		"stratusCloudScrollU": 0,
		"stratusCloudScrollV": 0,
		"stratusCloudHeight": 0,
		"cumulusCloudTiling": 0,
		"cumulusCloudScrollU": 0,
		"cumulusCloudScrollV": 0,
		"cumulusCloudHeight": 0,
		"cloudAnimationSpeed": 0.4148843259266868,
		"cloudSilverLiningThickness": 0.11372870445045354,
		"cloudSilverLiningBrightness": 1.4376854877886265,
		"cloudShadows": 0
	}
}